[
  {
    "RmlResult": null,
    "LuisResult": {
      "Message": "twa 81 identified cleared st rolampont flight level 340",
      "CallSign": {
        "Airline": "twa",
        "FlightNumber": "81"
      },
      "Intents": {
        "None": {
          "Score": 0.025359944
        },
        "Contact": {
          "Frequency": null,
          "Place": null,
          "Score": 0.023052696
        },
        "FlightLevel": {
          "Instruction": null,
          "Level": "340",
          "Score": 0.7732336
        },
        "Squawk": {
          "Code": null,
          "Score": 0.0051931166
        },
        "Turn": {
          "Direction": null,
          "Degrees": null,
          "Heading": null,
          "Place": null,
          "Score": 0.03644986
        }
      }
    }
  }
]