{"source":"sm2_02_047.wav","timestamp":"2021-03-17T07:49:01Z","durationInTicks":43900000,"duration":"PT4.39S","combinedRecognizedPhrases":[{"channel":0,"lexical":"lufthansa four two zero seven contact rhein one three two decimal four","itn":"lufthansa 4207 contact rhein 132 decimal 4","maskedITN":"lufthansa 4207 contact rhein 132 decimal 4","display":"Lufthansa 4207 contact Rhein 132, decimal 4."}],"recognizedPhrases":[{"recognitionStatus":"Success","channel":0,"offset":"PT0.41S","duration":"PT3.98S","offsetInTicks":4100000,"durationInTicks":39800000,"nBest":[{"confidence":0.86987686,"lexical":"lufthansa four two zero seven contact rhein one three two decimal four","itn":"lufthansa 4207 contact rhein 132 decimal 4","maskedITN":"lufthansa 4207 contact rhein 132 decimal 4","display":"Lufthansa 4207 contact Rhein 132, decimal 4.","words":[{"word":"lufthansa","offset":"PT0.45S","duration":"PT0.46S","offsetInTicks":4500000,"durationInTicks":4600000,"confidence":0.91794},{"word":"four","offset":"PT0.93S","duration":"PT0.23S","offsetInTicks":9300000,"durationInTicks":2300000,"confidence":0.936374},{"word":"two","offset":"PT1.18S","duration":"PT0.12S","offsetInTicks":11800000,"durationInTicks":1200000,"confidence":0.92705},{"word":"zero","offset":"PT1.32S","duration":"PT0.25S","offsetInTicks":13200000,"durationInTicks":2500000,"confidence":0.975968},{"word":"seven","offset":"PT1.59S","duration":"PT0.42S","offsetInTicks":15900000,"durationInTicks":4200000,"confidence":0.926314},{"word":"contact","offset":"PT2.03S","duration":"PT0.53S","offsetInTicks":20300000,"durationInTicks":5300000,"confidence":0.965154},{"word":"rhein","offset":"PT2.58S","duration":"PT0.27S","offsetInTicks":25800000,"durationInTicks":2700000,"confidence":0.460362},{"word":"one","offset":"PT2.87S","duration":"PT0.13S","offsetInTicks":28700000,"durationInTicks":1300000,"confidence":0.837088},{"word":"three","offset":"PT3S","duration":"PT0.19S","offsetInTicks":30000000,"durationInTicks":1900000,"confidence":0.924712},{"word":"two","offset":"PT3.19S","duration":"PT0.18S","offsetInTicks":31900000,"durationInTicks":1800000,"confidence":0.865469},{"word":"decimal","offset":"PT3.37S","duration":"PT0.36S","offsetInTicks":33700000,"durationInTicks":3600000,"confidence":0.693309},{"word":"four","offset":"PT3.75S","duration":"PT0.44S","offsetInTicks":37500000,"durationInTicks":4400000,"confidence":0.923929}]}]}]}