{"source":"sm3_01_163.wav","timestamp":"2021-03-17T07:49:01Z","durationInTicks":33800000,"duration":"PT3.38S","combinedRecognizedPhrases":[{"channel":0,"lexical":"hapag lloyd one three seven guten tag radar contact","itn":"hapag lloyd 137 guten tag radar contact","maskedITN":"hapag lloyd 137 guten tag radar contact","display":"Hapag, Lloyd 137 guten tag radar contact."}],"recognizedPhrases":[{"recognitionStatus":"Success","channel":0,"offset":"PT0.32S","duration":"PT2.52S","offsetInTicks":3200000,"durationInTicks":25200000,"nBest":[{"confidence":0.8180393,"lexical":"hapag lloyd one three seven guten tag radar contact","itn":"hapag lloyd 137 guten tag radar contact","maskedITN":"hapag lloyd 137 guten tag radar contact","display":"Hapag, Lloyd 137 guten tag radar contact.","words":[{"word":"hapag","offset":"PT0.37S","duration":"PT0.32S","offsetInTicks":3700000,"durationInTicks":3200000,"confidence":0.607197},{"word":"lloyd","offset":"PT0.69S","duration":"PT0.23S","offsetInTicks":6900000,"durationInTicks":2300000,"confidence":0.914356},{"word":"one","offset":"PT0.92S","duration":"PT0.18S","offsetInTicks":9200000,"durationInTicks":1800000,"confidence":0.852636},{"word":"three","offset":"PT1.1S","duration":"PT0.22S","offsetInTicks":11000000,"durationInTicks":2200000,"confidence":0.891293},{"word":"seven","offset":"PT1.32S","duration":"PT0.28S","offsetInTicks":13200000,"durationInTicks":2800000,"confidence":0.87296},{"word":"guten","offset":"PT1.6S","duration":"PT0.26S","offsetInTicks":16000000,"durationInTicks":2600000,"confidence":0.518018},{"word":"tag","offset":"PT1.86S","duration":"PT0.28S","offsetInTicks":18600000,"durationInTicks":2800000,"confidence":0.900657},{"word":"radar","offset":"PT2.16S","duration":"PT0.22S","offsetInTicks":21600000,"durationInTicks":2200000,"confidence":0.813915},{"word":"contact","offset":"PT2.38S","duration":"PT0.44S","offsetInTicks":23800000,"durationInTicks":4400000,"confidence":0.962075}]}]}]}