{"source":"sm4_04_217.wav","timestamp":"2021-03-17T07:49:01Z","durationInTicks":26700000,"duration":"PT2.67S","combinedRecognizedPhrases":[{"channel":0,"lexical":"alitalia four one three direct trasadingen","itn":"alitalia 413 direct trasadingen","maskedITN":"alitalia 413 direct trasadingen","display":"Alitalia 413 direct trasadingen."}],"recognizedPhrases":[{"recognitionStatus":"Success","channel":0,"offset":"PT0.18S","duration":"PT2.49S","offsetInTicks":1800000,"durationInTicks":24900000,"nBest":[{"confidence":0.8815792,"lexical":"alitalia four one three direct trasadingen","itn":"alitalia 413 direct trasadingen","maskedITN":"alitalia 413 direct trasadingen","display":"Alitalia 413 direct trasadingen.","words":[{"word":"alitalia","offset":"PT0.24S","duration":"PT0.44S","offsetInTicks":2400000,"durationInTicks":4400000,"confidence":0.932444},{"word":"four","offset":"PT0.7S","duration":"PT0.18S","offsetInTicks":7000000,"durationInTicks":1800000,"confidence":0.835639},{"word":"one","offset":"PT0.88S","duration":"PT0.14S","offsetInTicks":8800000,"durationInTicks":1400000,"confidence":0.848489},{"word":"three","offset":"PT1.02S","duration":"PT0.24S","offsetInTicks":10200000,"durationInTicks":2400000,"confidence":0.904306},{"word":"direct","offset":"PT1.26S","duration":"PT0.46S","offsetInTicks":12600000,"durationInTicks":4600000,"confidence":0.833679},{"word":"trasadingen","offset":"PT1.74S","duration":"PT0.62S","offsetInTicks":17400000,"durationInTicks":6200000,"confidence":0.893033}]}]}]}