{"source":"zf1_06_081.wav","timestamp":"2021-03-17T07:49:01Z","durationInTicks":40500000,"duration":"PT4.05S","combinedRecognizedPhrases":[{"channel":0,"lexical":"transwede one zero seven good morning maintain three three zero trasadingen three","itn":"transwede 107 good morning maintain 330 trasadingen 3","maskedITN":"transwede 107 good morning maintain 330 trasadingen 3","display":"Transwede 107 good morning maintain 330 trasadingen 3."}],"recognizedPhrases":[{"recognitionStatus":"Success","channel":0,"offset":"PT0.12S","duration":"PT3.93S","offsetInTicks":1200000,"durationInTicks":39300000,"nBest":[{"confidence":0.85377187,"lexical":"transwede one zero seven good morning maintain three three zero trasadingen three","itn":"transwede 107 good morning maintain 330 trasadingen 3","maskedITN":"transwede 107 good morning maintain 330 trasadingen 3","display":"Transwede 107 good morning maintain 330 trasadingen 3.","words":[{"word":"transwede","offset":"PT0.15S","duration":"PT0.55S","offsetInTicks":1500000,"durationInTicks":5500000,"confidence":0.914223},{"word":"one","offset":"PT0.7S","duration":"PT0.21S","offsetInTicks":7000000,"durationInTicks":2100000,"confidence":0.884682},{"word":"zero","offset":"PT0.91S","duration":"PT0.29S","offsetInTicks":9100000,"durationInTicks":2900000,"confidence":0.951558},{"word":"seven","offset":"PT1.2S","duration":"PT0.3S","offsetInTicks":12000000,"durationInTicks":3000000,"confidence":0.884892},{"word":"good","offset":"PT1.5S","duration":"PT0.16S","offsetInTicks":15000000,"durationInTicks":1600000,"confidence":0.743675},{"word":"morning","offset":"PT1.66S","duration":"PT0.31S","offsetInTicks":16600000,"durationInTicks":3100000,"confidence":0.903863},{"word":"maintain","offset":"PT1.97S","duration":"PT0.33S","offsetInTicks":19700000,"durationInTicks":3300000,"confidence":0.83822},{"word":"three","offset":"PT2.3S","duration":"PT0.19S","offsetInTicks":23000000,"durationInTicks":1900000,"confidence":0.889325},{"word":"three","offset":"PT2.49S","duration":"PT0.21S","offsetInTicks":24900000,"durationInTicks":2100000,"confidence":0.928658},{"word":"zero","offset":"PT2.7S","duration":"PT0.3S","offsetInTicks":27000000,"durationInTicks":3000000,"confidence":0.970573},{"word":"trasadingen","offset":"PT3.02S","duration":"PT0.56S","offsetInTicks":30200000,"durationInTicks":5600000,"confidence":0.685596},{"word":"three","offset":"PT3.58S","duration":"PT0.28S","offsetInTicks":35800000,"durationInTicks":2800000,"confidence":0.733926}]}]}]}