[
  {
    "RmlResult": null,
    "LuisResult": {
      "Message": "belgian air force 334 contact reims 134.4 if",
      "CallSign": {
        "Airline": "belgian air force",
        "FlightNumber": "334"
      },
      "Intents": {
        "None": {
          "Score": 0.018915895
        },
        "Contact": {
          "Frequency": "134.4",
          "Place": "reims",
          "Score": 0.76874393
        },
        "FlightLevel": {
          "Instruction": null,
          "Level": null,
          "Score": 0.040494233
        },
        "Squawk": {
          "Code": null,
          "Score": 0.0067563113
        },
        "Turn": {
          "Direction": null,
          "Degrees": null,
          "Heading": null,
          "Place": null,
          "Score": 0.05528571
        }
      }
    }
  }
]