[
  {
    "RmlResult": null,
    "LuisResult": {
      "Message": "sabena 801 right turn to trasadingen",
      "CallSign": {
        "Airline": "sabena",
        "FlightNumber": "801"
      },
      "Intents": {
        "None": {
          "Score": 0.070704
        },
        "Contact": {
          "Frequency": null,
          "Place": null,
          "Score": 0.0019424172
        },
        "FlightLevel": {
          "Instruction": null,
          "Level": null,
          "Score": 0.0016879176
        },
        "Squawk": {
          "Code": null,
          "Score": 0.0019555097
        },
        "Turn": {
          "Direction": null,
          "Degrees": null,
          "Heading": null,
          "Place": null,
          "Score": 0.0027792072
        }
      }
    }
  }
]