{"source":"gf1_01_005.wav","timestamp":"2021-03-17T07:48:56Z","durationInTicks":32500000,"duration":"PT3.25S","combinedRecognizedPhrases":[{"channel":0,"lexical":"lufthansa four seven two three resume own navigation to willisau","itn":"lufthansa 4723 resume own navigation to willisau","maskedITN":"lufthansa 4723 resume own navigation to willisau","display":"Lufthansa 4723 resume. Own navigation to Willisau."}],"recognizedPhrases":[{"recognitionStatus":"Success","channel":0,"offset":"PT0.12S","duration":"PT3.13S","offsetInTicks":1200000,"durationInTicks":31300000,"nBest":[{"confidence":0.82392144,"lexical":"lufthansa four seven two three resume own navigation to willisau","itn":"lufthansa 4723 resume own navigation to willisau","maskedITN":"lufthansa 4723 resume own navigation to willisau","display":"Lufthansa 4723 resume. Own navigation to Willisau.","words":[{"word":"lufthansa","offset":"PT0.14S","duration":"PT0.48S","offsetInTicks":1400000,"durationInTicks":4800000,"confidence":0.922351},{"word":"four","offset":"PT0.64S","duration":"PT0.2S","offsetInTicks":6400000,"durationInTicks":2000000,"confidence":0.85837},{"word":"seven","offset":"PT0.84S","duration":"PT0.26S","offsetInTicks":8400000,"durationInTicks":2600000,"confidence":0.8885},{"word":"two","offset":"PT1.1S","duration":"PT0.16S","offsetInTicks":11000000,"durationInTicks":1600000,"confidence":0.847856},{"word":"three","offset":"PT1.26S","duration":"PT0.22S","offsetInTicks":12600000,"durationInTicks":2200000,"confidence":0.919639},{"word":"resume","offset":"PT1.48S","duration":"PT0.31S","offsetInTicks":14800000,"durationInTicks":3100000,"confidence":0.701316},{"word":"own","offset":"PT1.79S","duration":"PT0.11S","offsetInTicks":17900000,"durationInTicks":1100000,"confidence":0.653866},{"word":"navigation","offset":"PT1.9S","duration":"PT0.58S","offsetInTicks":19000000,"durationInTicks":5800000,"confidence":0.931541},{"word":"to","offset":"PT2.48S","duration":"PT0.12S","offsetInTicks":24800000,"durationInTicks":1200000,"confidence":0.797017},{"word":"willisau","offset":"PT2.6S","duration":"PT0.6S","offsetInTicks":26000000,"durationInTicks":6000000,"confidence":0.660103}]}]}]}