{"source":"sm1_04_095.wav","timestamp":"2021-03-17T07:48:56Z","durationInTicks":37200000,"duration":"PT3.72S","combinedRecognizedPhrases":[{"channel":0,"lexical":"sabena seven eight one six contact rhein one two seven three seven","itn":"sabena 7816 contact rhein 12737","maskedITN":"sabena 7816 contact rhein 12737","display":"Sabena 7816 contact Rhein 12737."}],"recognizedPhrases":[{"recognitionStatus":"Success","channel":0,"offset":"PT0.02S","duration":"PT3.7S","offsetInTicks":200000,"durationInTicks":37000000,"nBest":[{"confidence":0.8449839,"lexical":"sabena seven eight one six contact rhein one two seven three seven","itn":"sabena 7816 contact rhein 12737","maskedITN":"sabena 7816 contact rhein 12737","display":"Sabena 7816 contact Rhein 12737.","words":[{"word":"sabena","offset":"PT0.04S","duration":"PT0.58S","offsetInTicks":400000,"durationInTicks":5800000,"confidence":0.696639},{"word":"seven","offset":"PT0.62S","duration":"PT0.3S","offsetInTicks":6200000,"durationInTicks":3000000,"confidence":0.87298},{"word":"eight","offset":"PT0.92S","duration":"PT0.12S","offsetInTicks":9200000,"durationInTicks":1200000,"confidence":0.904129},{"word":"one","offset":"PT1.04S","duration":"PT0.16S","offsetInTicks":10400000,"durationInTicks":1600000,"confidence":0.902479},{"word":"six","offset":"PT1.2S","duration":"PT0.24S","offsetInTicks":12000000,"durationInTicks":2400000,"confidence":0.923838},{"word":"contact","offset":"PT1.44S","duration":"PT0.4S","offsetInTicks":14400000,"durationInTicks":4000000,"confidence":0.87324},{"word":"rhein","offset":"PT1.84S","duration":"PT0.21S","offsetInTicks":18400000,"durationInTicks":2100000,"confidence":0.464162},{"word":"one","offset":"PT2.07S","duration":"PT0.14S","offsetInTicks":20700000,"durationInTicks":1400000,"confidence":0.856978},{"word":"two","offset":"PT2.21S","duration":"PT0.23S","offsetInTicks":22100000,"durationInTicks":2300000,"confidence":0.918933},{"word":"seven","offset":"PT2.44S","duration":"PT0.32S","offsetInTicks":24400000,"durationInTicks":3200000,"confidence":0.928278},{"word":"three","offset":"PT2.76S","duration":"PT0.24S","offsetInTicks":27600000,"durationInTicks":2400000,"confidence":0.919113},{"word":"seven","offset":"PT3S","duration":"PT0.44S","offsetInTicks":30000000,"durationInTicks":4400000,"confidence":0.953978}]}]}]}