{"source":"sm1_02_082.wav","timestamp":"2021-03-17T07:48:56Z","durationInTicks":33500000,"duration":"PT3.35S","combinedRecognizedPhrases":[{"channel":0,"lexical":"britannia triple two alfa rhein radar identified","itn":"britannia triple 2A rhein radar identified","maskedITN":"britannia triple 2a rhein radar identified","display":"Britannia Triple 2A Rhein radar identified."}],"recognizedPhrases":[{"recognitionStatus":"Success","channel":0,"offset":"PT0.04S","duration":"PT3.31S","offsetInTicks":400000,"durationInTicks":33100000,"nBest":[{"confidence":0.8677124,"lexical":"britannia triple two alfa rhein radar identified","itn":"britannia triple 2A rhein radar identified","maskedITN":"britannia triple 2a rhein radar identified","display":"Britannia Triple 2A Rhein radar identified.","words":[{"word":"britannia","offset":"PT0.06S","duration":"PT0.53S","offsetInTicks":600000,"durationInTicks":5300000,"confidence":0.925363},{"word":"triple","offset":"PT0.61S","duration":"PT0.29S","offsetInTicks":6100000,"durationInTicks":2900000,"confidence":0.753107},{"word":"two","offset":"PT0.9S","duration":"PT0.21S","offsetInTicks":9000000,"durationInTicks":2100000,"confidence":0.9569},{"word":"alfa","offset":"PT1.13S","duration":"PT0.41S","offsetInTicks":11300000,"durationInTicks":4100000,"confidence":0.887001},{"word":"rhein","offset":"PT1.56S","duration":"PT0.26S","offsetInTicks":15600000,"durationInTicks":2600000,"confidence":0.433287},{"word":"radar","offset":"PT1.82S","duration":"PT0.36S","offsetInTicks":18200000,"durationInTicks":3600000,"confidence":0.925853},{"word":"identified","offset":"PT2.18S","duration":"PT0.82S","offsetInTicks":21800000,"durationInTicks":8200000,"confidence":0.950716}]}]}]}