{"source":"sm4_05_015.wav","timestamp":"2021-03-17T07:48:56Z","durationInTicks":55100000,"duration":"PT5.51S","combinedRecognizedPhrases":[{"channel":0,"lexical":"sabena four eight one contact rhein frequency one three two decimal four tschuss","itn":"sabena 481 contact rhein frequency 132 decimal 4 tschuss","maskedITN":"sabena 481 contact rhein frequency 132 decimal 4 tschuss","display":"Sabena 481 contact Rhein frequency 132 decimal 4 tschuss."}],"recognizedPhrases":[{"recognitionStatus":"Success","channel":0,"offset":"PT0.12S","duration":"PT5.39S","offsetInTicks":1200000,"durationInTicks":53900000,"nBest":[{"confidence":0.80345774,"lexical":"sabena four eight one contact rhein frequency one three two decimal four tschuss","itn":"sabena 481 contact rhein frequency 132 decimal 4 tschuss","maskedITN":"sabena 481 contact rhein frequency 132 decimal 4 tschuss","display":"Sabena 481 contact Rhein frequency 132 decimal 4 tschuss.","words":[{"word":"sabena","offset":"PT0.14S","duration":"PT0.4S","offsetInTicks":1400000,"durationInTicks":4000000,"confidence":0.530106},{"word":"four","offset":"PT0.54S","duration":"PT0.2S","offsetInTicks":5400000,"durationInTicks":2000000,"confidence":0.865202},{"word":"eight","offset":"PT0.76S","duration":"PT0.08S","offsetInTicks":7600000,"durationInTicks":800000,"confidence":0.835207},{"word":"one","offset":"PT0.84S","duration":"PT0.22S","offsetInTicks":8400000,"durationInTicks":2200000,"confidence":0.874578},{"word":"contact","offset":"PT1.06S","duration":"PT0.4S","offsetInTicks":10600000,"durationInTicks":4000000,"confidence":0.945494},{"word":"rhein","offset":"PT1.48S","duration":"PT0.4S","offsetInTicks":14800000,"durationInTicks":4000000,"confidence":0.410467},{"word":"frequency","offset":"PT1.9S","duration":"PT0.98S","offsetInTicks":19000000,"durationInTicks":9800000,"confidence":0.936907},{"word":"one","offset":"PT3.16S","duration":"PT0.32S","offsetInTicks":31600000,"durationInTicks":3200000,"confidence":0.956122},{"word":"three","offset":"PT3.54S","duration":"PT0.3S","offsetInTicks":35400000,"durationInTicks":3000000,"confidence":0.959102},{"word":"two","offset":"PT3.86S","duration":"PT0.28S","offsetInTicks":38600000,"durationInTicks":2800000,"confidence":0.952041},{"word":"decimal","offset":"PT4.16S","duration":"PT0.45S","offsetInTicks":41600000,"durationInTicks":4500000,"confidence":0.913683},{"word":"four","offset":"PT4.61S","duration":"PT0.39S","offsetInTicks":46100000,"durationInTicks":3900000,"confidence":0.893746},{"word":"tschuss","offset":"PT5.03S","duration":"PT0.41S","offsetInTicks":50300000,"durationInTicks":4100000,"confidence":0.38015}]}]}]}