{"source":"sm4_03_090.wav","timestamp":"2021-03-17T07:48:56Z","durationInTicks":23200000,"duration":"PT2.32S","combinedRecognizedPhrases":[{"channel":0,"lexical":"tag alitalia two nine one identified","itn":"tag alitalia 291 identified","maskedITN":"tag alitalia 291 identified","display":"Tag Alitalia 291 identified."}],"recognizedPhrases":[{"recognitionStatus":"Success","channel":0,"offset":"PT0.03S","duration":"PT2.29S","offsetInTicks":300000,"durationInTicks":22900000,"nBest":[{"confidence":0.8822962,"lexical":"tag alitalia two nine one identified","itn":"tag alitalia 291 identified","maskedITN":"tag alitalia 291 identified","display":"Tag Alitalia 291 identified.","words":[{"word":"tag","offset":"PT0.05S","duration":"PT0.27S","offsetInTicks":500000,"durationInTicks":2700000,"confidence":0.62164},{"word":"alitalia","offset":"PT0.32S","duration":"PT0.47S","offsetInTicks":3200000,"durationInTicks":4700000,"confidence":0.942197},{"word":"two","offset":"PT0.81S","duration":"PT0.16S","offsetInTicks":8100000,"durationInTicks":1600000,"confidence":0.768238},{"word":"nine","offset":"PT0.97S","duration":"PT0.2S","offsetInTicks":9700000,"durationInTicks":2000000,"confidence":0.950607},{"word":"one","offset":"PT1.19S","duration":"PT0.22S","offsetInTicks":11900000,"durationInTicks":2200000,"confidence":0.871434},{"word":"identified","offset":"PT1.41S","duration":"PT0.72S","offsetInTicks":14100000,"durationInTicks":7200000,"confidence":0.950631}]}]}]}