{"source":"zf1_01_107.wav","timestamp":"2021-03-17T07:48:56Z","durationInTicks":28700000,"duration":"PT2.87S","combinedRecognizedPhrases":[{"channel":0,"lexical":"jetcom one three three oh navigation to fusse","itn":"jetcom 1330 navigation to fusse","maskedITN":"jetcom 1330 navigation to fusse","display":"Jetcom 1330 navigation to fusse."}],"recognizedPhrases":[{"recognitionStatus":"Success","channel":0,"offset":"PT0.04S","duration":"PT2.83S","offsetInTicks":400000,"durationInTicks":28300000,"nBest":[{"confidence":0.6928906,"lexical":"jetcom one three three oh navigation to fusse","itn":"jetcom 1330 navigation to fusse","maskedITN":"jetcom 1330 navigation to fusse","display":"Jetcom 1330 navigation to fusse.","words":[{"word":"jetcom","offset":"PT0.13S","duration":"PT0.54S","offsetInTicks":1300000,"durationInTicks":5400000,"confidence":0.499023},{"word":"one","offset":"PT0.67S","duration":"PT0.19S","offsetInTicks":6700000,"durationInTicks":1900000,"confidence":0.896955},{"word":"three","offset":"PT0.86S","duration":"PT0.2S","offsetInTicks":8600000,"durationInTicks":2000000,"confidence":0.939257},{"word":"three","offset":"PT1.06S","duration":"PT0.3S","offsetInTicks":10600000,"durationInTicks":3000000,"confidence":0.966156},{"word":"oh","offset":"PT1.38S","duration":"PT0.12S","offsetInTicks":13800000,"durationInTicks":1200000,"confidence":0.884377},{"word":"navigation","offset":"PT1.5S","duration":"PT0.48S","offsetInTicks":15000000,"durationInTicks":4800000,"confidence":0.819358},{"word":"to","offset":"PT2S","duration":"PT0.13S","offsetInTicks":20000000,"durationInTicks":1300000,"confidence":0.851305},{"word":"fusse","offset":"PT2.15S","duration":"PT0.51S","offsetInTicks":21500000,"durationInTicks":5100000,"confidence":0.360316}]}]}]}