[
  {
    "LuisContext": {
      "Message": "speedbird 569 bonjour squawk 5763",
      "CallSign": {
        "Airline": "speedbird",
        "FlightNumber": "569"
      },
      "Intents": {
        "None": {
          "Score": 0.023390608
        },
        "Contact": {
          "Frequency": null,
          "Place": null,
          "Score": 0.0013007676
        },
        "FlightLevel": {
          "Instruction": null,
          "Level": null,
          "Score": 0.001617041
        },
        "Squawk": {
          "Code": "5763",
          "Score": 0.9806249
        },
        "Turn": {
          "Direction": null,
          "Degrees": null,
          "Heading": null,
          "Place": null,
          "Score": 0.0013128972
        }
      }
    },
    "RmlContext": {
      "Message": "speedbird 569 bonjour squawk 5763",
      "CallSign": {
        "Airline": "speedbird",
        "FlightNumber": "569"
      },
      "Intents": {
        "Squawk": {
          "Code": "5763",
          "Score": 1.0
        }
      }
    }
  },
  {
    "LuisContext": {
      "Message": "speedbird 56 bonjour squawk 5763",
      "CallSign": null,
      "Intents": {
        "None": {
          "Score": 0.020447737
        },
        "Contact": {
          "Frequency": null,
          "Place": null,
          "Score": 0.0012620086
        },
        "FlightLevel": {
          "Instruction": null,
          "Level": null,
          "Score": 0.0016045764
        },
        "Squawk": {
          "Code": "5763",
          "Score": 0.9833479
        },
        "Turn": {
          "Direction": null,
          "Degrees": null,
          "Heading": null,
          "Place": null,
          "Score": 0.0012728726
        }
      }
    },
    "RmlContext": {
      "Message": "speedbird 56 bonjour squawk 5763",
      "CallSign": {
        "Airline": "speedbird",
        "FlightNumber": "56"
      },
      "Intents": {
        "Squawk": {
          "Code": "5763",
          "Score": 1.0
        }
      }
    }
  },
  {
    "LuisContext": {
      "Message": "speedbird 569 bonjour squawk 5763",
      "CallSign": {
        "Airline": "speedbird",
        "FlightNumber": "569"
      },
      "Intents": {
        "None": {
          "Score": 0.023390608
        },
        "Contact": {
          "Frequency": null,
          "Place": null,
          "Score": 0.0013007676
        },
        "FlightLevel": {
          "Instruction": null,
          "Level": null,
          "Score": 0.001617041
        },
        "Squawk": {
          "Code": "5763",
          "Score": 0.9806249
        },
        "Turn": {
          "Direction": null,
          "Degrees": null,
          "Heading": null,
          "Place": null,
          "Score": 0.0013128972
        }
      }
    },
    "RmlContext": {
      "Message": "speedbird 569 bonjour squawk 5763",
      "CallSign": {
        "Airline": "speedbird",
        "FlightNumber": "569"
      },
      "Intents": {
        "Squawk": {
          "Code": "5763",
          "Score": 1.0
        }
      }
    }
  }
]